majority/or_gate.vhdl
library IEEE;
use IEEE.STD_LOGIC_1164.ALL;


entity or_gate is
    port(
        or_input : in std_logic_vector(1 DOWNTO 0);
        or_out: out std_logic
    	);
end or_gate;
    

architecture Behavioral of or_gate is
	
    begin
        process(or_input) is begin
            case(or_input) is 
                when "00" => or_out <= '0';
                when others => or_out <= '1';
            end case ;
        end process;
    
end Behavioral;

majority/and_gate.vhdl
library IEEE;
use IEEE.STD_LOGIC_1164.ALL;


entity and_gate is
    port(
        and_input : in std_logic_vector(1 DOWNTO 0);
        and_out: out std_logic
    	);
end and_gate;
    

architecture Behavioral of and_gate is
	
    begin
        process(and_input) begin
            case(and_input) is 
                when "11" => and_out <= '1';
                when others => and_out <= '0';
            end case ;
        end process;
    
end Behavioral;

majority/majority.vhdl
library IEEE;
use IEEE.STD_LOGIC_1164.ALL;


entity majority is
    port(
        m_input : in std_logic_vector(2 DOWNTO 0);
        majority_bit: out std_logic
    );
    end majority;


architecture Behavioral of majority is
    begin
        process (m_input)
        begin
            case(m_input) is
                when "000" => majority_bit <= '0';
                when "001" => majority_bit <= '0';
                when "010" => majority_bit <= '0';
                when "011" => majority_bit <= '1';
                when "100" => majority_bit <= '0';
                when "101" => majority_bit <= '1';
                when "110" => majority_bit <= '1';
                when "111" => majority_bit <= '1';
                when others => majority_bit <= '0';
            end case;
        end process;
end Behavioral;


architecture Behavioral1 of majority is

begin
	process (m_input) is begin
      case(m_input) is 
          when "011" => majority_bit <= '1';
          when "101" => majority_bit <= '1';
          when "110" => majority_bit <= '1';
          when "111" => majority_bit <= '1';
          when others => majority_bit <= '0';
      end case ;
    end process;

end Behavioral1;


architecture Behavioral2 of majority is

begin
    process (m_input) begin
        if m_input = "011" or m_input = "101" or m_input = "110" or m_input = "111" then
            majority_bit <= '1';
        else
            majority_bit <= '0';
        end if;
    end process;

end Behavioral2;


architecture Behavioral3 of majority is

begin
    with m_input select
      majority_bit <= '1' when "011",
                      '1' when "101",
                      '1' when "110",
                      '1' when "111",
                      '0' when OTHERS;
end Behavioral3;


architecture Behavioral4 of majority is
    -- these signals represent all possible permutations of any two inputs
    signal permutation_1: std_logic_vector(1 downto 0);
    signal permutation_2: std_logic_vector(1 downto 0);
    signal permutation_3: std_logic_vector(1 downto 0);
    
    begin
        -- here we assign the values of the input to the appropriate signals
        permutation_1 <= m_input(2 downto 1);
        permutation_2 <= m_input(1 downto 0);
        -- here we need to use the concatenation opeartor to get the proper permutation
        permutation_3 <= m_input(2)&m_input(0);

        process (m_input) begin
            if permutation_3 = "11" or permutation_2 = "11" or permutation_3 = "11" then
                majority_bit <= '1';
            else
                majority_bit <= '0';
            end if;
        end process;          
end Behavioral4;

    
    
architecture Structural of majority is

    signal and_1_out, and_2_out, and_3_out, or_1_out, or_2_out: std_logic:='0';
    
begin

and1: entity work.and_gate(Behavioral) port map (and_input => m_input(2 downto 1), and_out => and_1_out);
and2: entity work.and_gate(Behavioral) port map (and_input => m_input(1 downto 0), and_out => and_2_out);
and3: entity work.and_gate(Behavioral) port map (and_input(0) => m_input(0), and_input(1) => m_input(2) , and_out => and_3_out);
or1:  entity work.or_gate(Behavioral) port map (or_input(0) => and_1_out, or_input(1) => and_2_out , or_out => or_1_out);
or2:  entity work.or_gate(Behavioral) port map (or_input(0) => or_1_out, or_input(1) => and_3_out , or_out => majority_bit);

end Structural;

majority/majority_tb.vhdl
library IEEE;
use IEEE.STD_LOGIC_1164.ALL;
USE IEEE.NUMERIC_STD.ALL;

entity majority_tb is
end majority_tb;

architecture Behavioral of majority_tb is

    signal m_input : std_logic_vector(2 downto 0):="000";
    signal majority_bit: std_logic:='0';

begin

UUT: entity work.majority(Behavioral1) PORT map(m_input => m_input, majority_bit => majority_bit);
    
STIMULUS: process begin
    FOR i IN 0 TO 7 LOOP
    	m_input <= STD_LOGIC_VECTOR(TO_UNSIGNED(i, m_input'length));
        WAIT FOR 10 NS;
    END LOOP;
    WAIT;
end process;

end Behavioral;

majority/majority.vcd
$date
  Thu Oct 20 11:08:04 2022
$end
$version
  GHDL v0
$end
$timescale
  1 fs
$end
$scope module standard $end
$upscope $end
$scope module std_logic_1164 $end
$upscope $end
$scope module numeric_std $end
$upscope $end
$scope module majority_tb $end
$var reg 3 ! m_input[2:0] $end
$var reg 1 " majority_bit $end
$scope module uut $end
$var reg 3 # m_input[2:0] $end
$var reg 1 $ majority_bit $end
$upscope $end
$upscope $end
$enddefinitions $end
#0
b000 !
0"
b000 #
0$
#10000000
b001 !
b001 #
#20000000
b010 !
b010 #
#30000000
b011 !
1"
b011 #
1$
#40000000
b100 !
0"
b100 #
0$
#50000000
b101 !
1"
b101 #
1$
#60000000
b110 !
b110 #
#70000000
b111 !
b111 #
