monotonic_counter/monotonic_counter.vhdl
LIBRARY IEEE;
USE IEEE.STD_LOGIC_1164.ALL;
use IEEE.numeric_std.all;


ENTITY monotonic_counter IS
	GENERIC(STOP_COUNT: natural:=9);
	PORT (
		reset : IN  STD_LOGIC;
		clock : IN  STD_LOGIC;
		count : OUT NATURAL
	);

END ENTITY monotonic_counter;


ARCHITECTURE Behavioral OF monotonic_counter IS

	SIGNAL n : natural := 0;

BEGIN
	count <= n;
	
	PROCESS (clock)
	BEGIN
		IF rising_edge(clock) THEN
			IF n = STOP_COUNT or reset = '1' THEN
				n <= 0;
			ELSE
				n <= n + 1;
			END IF;
		END IF;
	END PROCESS;
END ARCHITECTURE Behavioral;

monotonic_counter/monotonic_counter_tb.vhdl
LIBRARY IEEE;
USE IEEE.STD_LOGIC_1164.ALL;
USE IEEE.numeric_std.ALL;

ENTITY monotonic_counter_tb IS
END monotonic_counter_tb;

ARCHITECTURE Behavioral OF monotonic_counter_tb IS

	SIGNAL count            : INTEGER;
    SIGNAL reset : STD_LOGIC:='0';
	SIGNAL clock : STD_LOGIC;

BEGIN
	UUT : ENTITY work.monotonic_counter(Behavioral) GENERIC MAP(STOP_COUNT => 88) PORT MAP(reset => reset, clock => clock, count => count);
	reset <= '1' after 5 us;
	PROCESS
	BEGIN
		clock <= '1';
		WAIT FOR 5 ns;
		clock <= '0';
		WAIT FOR 5 ns;
        if reset = '1' then
            wait;
        end if;
	END PROCESS;

END Behavioral;

monotonic_counter/monotonic_counter.vcd
$date
  Thu Oct 20 11:46:45 2022
$end
$version
  GHDL v0
$end
$timescale
  1 fs
$end
$scope module standard $end
$upscope $end
$scope module std_logic_1164 $end
$upscope $end
$scope module numeric_std $end
$upscope $end
$scope module monotonic_counter_tb $end
$var integer 32 ! count $end
$var reg 1 " reset $end
$var reg 1 # clock $end
$scope module uut $end
$var reg 1 $ reset $end
$var reg 1 % clock $end
$var integer 32 & count $end
$var integer 32 ' n $end
$upscope $end
$upscope $end
$enddefinitions $end
#0
b0 !
0"
1#
0$
1%
b0 &
b0 '
#5000000
0#
0%
#10000000
b1 !
1#
1%
b1 &
b1 '
#15000000
0#
0%
#20000000
b10 !
1#
1%
b10 &
b10 '
#25000000
0#
0%
#30000000
b11 !
1#
1%
b11 &
b11 '
#35000000
0#
0%
#40000000
b100 !
1#
1%
b100 &
b100 '
#45000000
0#
0%
#50000000
b101 !
1#
1%
b101 &
b101 '
#55000000
0#
0%
#60000000
b110 !
1#
1%
b110 &
b110 '
#65000000
0#
0%
#70000000
b111 !
1#
1%
b111 &
b111 '
#75000000
0#
0%
#80000000
b1000 !
1#
1%
b1000 &
b1000 '
#85000000
0#
0%
#90000000
b1001 !
1#
1%
b1001 &
b1001 '
#95000000
0#
0%
#100000000
b1010 !
1#
1%
b1010 &
b1010 '
#105000000
0#
0%
#110000000
b1011 !
1#
1%
b1011 &
b1011 '
#115000000
0#
0%
#120000000
b1100 !
1#
1%
b1100 &
b1100 '
#125000000
0#
0%
#130000000
b1101 !
1#
1%
b1101 &
b1101 '
#135000000
0#
0%
#140000000
b1110 !
1#
1%
b1110 &
b1110 '
#145000000
0#
0%
#150000000
b1111 !
1#
1%
b1111 &
b1111 '
#155000000
0#
0%
#160000000
b10000 !
1#
1%
b10000 &
b10000 '
#165000000
0#
0%
#170000000
b10001 !
1#
1%
b10001 &
b10001 '
#175000000
0#
0%
#180000000
b10010 !
1#
1%
b10010 &
b10010 '
#185000000
0#
0%
#190000000
b10011 !
1#
1%
b10011 &
b10011 '
#195000000
0#
0%
#200000000
b10100 !
1#
1%
b10100 &
b10100 '
#205000000
0#
0%
#210000000
b10101 !
1#
1%
b10101 &
b10101 '
#215000000
0#
0%
#220000000
b10110 !
1#
1%
b10110 &
b10110 '
#225000000
0#
0%
#230000000
b10111 !
1#
1%
b10111 &
b10111 '
#235000000
0#
0%
#240000000
b11000 !
1#
1%
b11000 &
b11000 '
#245000000
0#
0%
#250000000
b11001 !
1#
1%
b11001 &
b11001 '
#255000000
0#
0%
#260000000
b11010 !
1#
1%
b11010 &
b11010 '
#265000000
0#
0%
#270000000
b11011 !
1#
1%
b11011 &
b11011 '
#275000000
0#
0%
#280000000
b11100 !
1#
1%
b11100 &
b11100 '
#285000000
0#
0%
#290000000
b11101 !
1#
1%
b11101 &
b11101 '
#295000000
0#
0%
#300000000
b11110 !
1#
1%
b11110 &
b11110 '
#305000000
0#
0%
#310000000
b11111 !
1#
1%
b11111 &
b11111 '
#315000000
0#
0%
#320000000
b100000 !
1#
1%
b100000 &
b100000 '
#325000000
0#
0%
#330000000
b100001 !
1#
1%
b100001 &
b100001 '
#335000000
0#
0%
#340000000
b100010 !
1#
1%
b100010 &
b100010 '
#345000000
0#
0%
#350000000
b100011 !
1#
1%
b100011 &
b100011 '
#355000000
0#
0%
#360000000
b100100 !
1#
1%
b100100 &
b100100 '
#365000000
0#
0%
#370000000
b100101 !
1#
1%
b100101 &
b100101 '
#375000000
0#
0%
#380000000
b100110 !
1#
1%
b100110 &
b100110 '
#385000000
0#
0%
#390000000
b100111 !
1#
1%
b100111 &
b100111 '
#395000000
0#
0%
#400000000
b101000 !
1#
1%
b101000 &
b101000 '
#405000000
0#
0%
#410000000
b101001 !
1#
1%
b101001 &
b101001 '
#415000000
0#
0%
#420000000
b101010 !
1#
1%
b101010 &
b101010 '
#425000000
0#
0%
#430000000
b101011 !
1#
1%
b101011 &
b101011 '
#435000000
0#
0%
#440000000
b101100 !
1#
1%
b101100 &
b101100 '
#445000000
0#
0%
#450000000
b101101 !
1#
1%
b101101 &
b101101 '
#455000000
0#
0%
#460000000
b101110 !
1#
1%
b101110 &
b101110 '
#465000000
0#
0%
#470000000
b101111 !
1#
1%
b101111 &
b101111 '
#475000000
0#
0%
#480000000
b110000 !
1#
1%
b110000 &
b110000 '
#485000000
0#
0%
#490000000
b110001 !
1#
1%
b110001 &
b110001 '
#495000000
0#
0%
#500000000
b110010 !
1#
1%
b110010 &
b110010 '
#505000000
0#
0%
#510000000
b110011 !
1#
1%
b110011 &
b110011 '
#515000000
0#
0%
#520000000
b110100 !
1#
1%
b110100 &
b110100 '
#525000000
0#
0%
#530000000
b110101 !
1#
1%
b110101 &
b110101 '
#535000000
0#
0%
#540000000
b110110 !
1#
1%
b110110 &
b110110 '
#545000000
0#
0%
#550000000
b110111 !
1#
1%
b110111 &
b110111 '
#555000000
0#
0%
#560000000
b111000 !
1#
1%
b111000 &
b111000 '
#565000000
0#
0%
#570000000
b111001 !
1#
1%
b111001 &
b111001 '
#575000000
0#
0%
#580000000
b111010 !
1#
1%
b111010 &
b111010 '
#585000000
0#
0%
#590000000
b111011 !
1#
1%
b111011 &
b111011 '
#595000000
0#
0%
#600000000
b111100 !
1#
1%
b111100 &
b111100 '
#605000000
0#
0%
#610000000
b111101 !
1#
1%
b111101 &
b111101 '
#615000000
0#
0%
#620000000
b111110 !
1#
1%
b111110 &
b111110 '
#625000000
0#
0%
#630000000
b111111 !
1#
1%
b111111 &
b111111 '
#635000000
0#
0%
#640000000
b1000000 !
1#
1%
b1000000 &
b1000000 '
#645000000
0#
0%
#650000000
b1000001 !
1#
1%
b1000001 &
b1000001 '
#655000000
0#
0%
#660000000
b1000010 !
1#
1%
b1000010 &
b1000010 '
#665000000
0#
0%
#670000000
b1000011 !
1#
1%
b1000011 &
b1000011 '
#675000000
0#
0%
#680000000
b1000100 !
1#
1%
b1000100 &
b1000100 '
#685000000
0#
0%
#690000000
b1000101 !
1#
1%
b1000101 &
b1000101 '
#695000000
0#
0%
#700000000
b1000110 !
1#
1%
b1000110 &
b1000110 '
#705000000
0#
0%
#710000000
b1000111 !
1#
1%
b1000111 &
b1000111 '
#715000000
0#
0%
#720000000
b1001000 !
1#
1%
b1001000 &
b1001000 '
#725000000
0#
0%
#730000000
b1001001 !
1#
1%
b1001001 &
b1001001 '
#735000000
0#
0%
#740000000
b1001010 !
1#
1%
b1001010 &
b1001010 '
#745000000
0#
0%
#750000000
b1001011 !
1#
1%
b1001011 &
b1001011 '
#755000000
0#
0%
#760000000
b1001100 !
1#
1%
b1001100 &
b1001100 '
#765000000
0#
0%
#770000000
b1001101 !
1#
1%
b1001101 &
b1001101 '
#775000000
0#
0%
#780000000
b1001110 !
1#
1%
b1001110 &
b1001110 '
#785000000
0#
0%
#790000000
b1001111 !
1#
1%
b1001111 &
b1001111 '
#795000000
0#
0%
#800000000
b1010000 !
1#
1%
b1010000 &
b1010000 '
#805000000
0#
0%
#810000000
b1010001 !
1#
1%
b1010001 &
b1010001 '
#815000000
0#
0%
#820000000
b1010010 !
1#
1%
b1010010 &
b1010010 '
#825000000
0#
0%
#830000000
b1010011 !
1#
1%
b1010011 &
b1010011 '
#835000000
0#
0%
#840000000
b1010100 !
1#
1%
b1010100 &
b1010100 '
#845000000
0#
0%
#850000000
b1010101 !
1#
1%
b1010101 &
b1010101 '
#855000000
0#
0%
#860000000
b1010110 !
1#
1%
b1010110 &
b1010110 '
#865000000
0#
0%
#870000000
b1010111 !
1#
1%
b1010111 &
b1010111 '
#875000000
0#
0%
#880000000
b1011000 !
1#
1%
b1011000 &
b1011000 '
#885000000
0#
0%
#890000000
b0 !
1#
1%
b0 &
b0 '
#895000000
0#
0%
#900000000
b1 !
1#
1%
b1 &
b1 '
#905000000
0#
0%
#910000000
b10 !
1#
1%
b10 &
b10 '
#915000000
0#
0%
#920000000
b11 !
1#
1%
b11 &
b11 '
#925000000
0#
0%
#930000000
b100 !
1#
1%
b100 &
b100 '
#935000000
0#
0%
#940000000
b101 !
1#
1%
b101 &
b101 '
#945000000
0#
0%
#950000000
b110 !
1#
1%
b110 &
b110 '
#955000000
0#
0%
#960000000
b111 !
1#
1%
b111 &
b111 '
#965000000
0#
0%
#970000000
b1000 !
1#
1%
b1000 &
b1000 '
#975000000
0#
0%
#980000000
b1001 !
1#
1%
b1001 &
b1001 '
#985000000
0#
0%
#990000000
b1010 !
1#
1%
b1010 &
b1010 '
#995000000
0#
0%
#1000000000
b1011 !
1#
1%
b1011 &
b1011 '
#1005000000
0#
0%
#1010000000
b1100 !
1#
1%
b1100 &
b1100 '
#1015000000
0#
0%
#1020000000
b1101 !
1#
1%
b1101 &
b1101 '
#1025000000
0#
0%
#1030000000
b1110 !
1#
1%
b1110 &
b1110 '
#1035000000
0#
0%
#1040000000
b1111 !
1#
1%
b1111 &
b1111 '
#1045000000
0#
0%
#1050000000
b10000 !
1#
1%
b10000 &
b10000 '
#1055000000
0#
0%
#1060000000
b10001 !
1#
1%
b10001 &
b10001 '
#1065000000
0#
0%
#1070000000
b10010 !
1#
1%
b10010 &
b10010 '
#1075000000
0#
0%
#1080000000
b10011 !
1#
1%
b10011 &
b10011 '
#1085000000
0#
0%
#1090000000
b10100 !
1#
1%
b10100 &
b10100 '
#1095000000
0#
0%
#1100000000
b10101 !
1#
1%
b10101 &
b10101 '
#1105000000
0#
0%
#1110000000
b10110 !
1#
1%
b10110 &
b10110 '
#1115000000
0#
0%
#1120000000
b10111 !
1#
1%
b10111 &
b10111 '
#1125000000
0#
0%
#1130000000
b11000 !
1#
1%
b11000 &
b11000 '
#1135000000
0#
0%
#1140000000
b11001 !
1#
1%
b11001 &
b11001 '
#1145000000
0#
0%
#1150000000
b11010 !
1#
1%
b11010 &
b11010 '
#1155000000
0#
0%
#1160000000
b11011 !
1#
1%
b11011 &
b11011 '
#1165000000
0#
0%
#1170000000
b11100 !
1#
1%
b11100 &
b11100 '
#1175000000
0#
0%
#1180000000
b11101 !
1#
1%
b11101 &
b11101 '
#1185000000
0#
0%
#1190000000
b11110 !
1#
1%
b11110 &
b11110 '
#1195000000
0#
0%
#1200000000
b11111 !
1#
1%
b11111 &
b11111 '
#1205000000
0#
0%
#1210000000
b100000 !
1#
1%
b100000 &
b100000 '
#1215000000
0#
0%
#1220000000
b100001 !
1#
1%
b100001 &
b100001 '
#1225000000
0#
0%
#1230000000
b100010 !
1#
1%
b100010 &
b100010 '
#1235000000
0#
0%
#1240000000
b100011 !
1#
1%
b100011 &
b100011 '
#1245000000
0#
0%
#1250000000
b100100 !
1#
1%
b100100 &
b100100 '
#1255000000
0#
0%
#1260000000
b100101 !
1#
1%
b100101 &
b100101 '
#1265000000
0#
0%
#1270000000
b100110 !
1#
1%
b100110 &
b100110 '
#1275000000
0#
0%
#1280000000
b100111 !
1#
1%
b100111 &
b100111 '
#1285000000
0#
0%
#1290000000
b101000 !
1#
1%
b101000 &
b101000 '
#1295000000
0#
0%
#1300000000
b101001 !
1#
1%
b101001 &
b101001 '
#1305000000
0#
0%
#1310000000
b101010 !
1#
1%
b101010 &
b101010 '
#1315000000
0#
0%
#1320000000
b101011 !
1#
1%
b101011 &
b101011 '
#1325000000
0#
0%
#1330000000
b101100 !
1#
1%
b101100 &
b101100 '
#1335000000
0#
0%
#1340000000
b101101 !
1#
1%
b101101 &
b101101 '
#1345000000
0#
0%
#1350000000
b101110 !
1#
1%
b101110 &
b101110 '
#1355000000
0#
0%
#1360000000
b101111 !
1#
1%
b101111 &
b101111 '
#1365000000
0#
0%
#1370000000
b110000 !
1#
1%
b110000 &
b110000 '
#1375000000
0#
0%
#1380000000
b110001 !
1#
1%
b110001 &
b110001 '
#1385000000
0#
0%
#1390000000
b110010 !
1#
1%
b110010 &
b110010 '
#1395000000
0#
0%
#1400000000
b110011 !
1#
1%
b110011 &
b110011 '
#1405000000
0#
0%
#1410000000
b110100 !
1#
1%
b110100 &
b110100 '
#1415000000
0#
0%
#1420000000
b110101 !
1#
1%
b110101 &
b110101 '
#1425000000
0#
0%
#1430000000
b110110 !
1#
1%
b110110 &
b110110 '
#1435000000
0#
0%
#1440000000
b110111 !
1#
1%
b110111 &
b110111 '
#1445000000
0#
0%
#1450000000
b111000 !
1#
1%
b111000 &
b111000 '
#1455000000
0#
0%
#1460000000
b111001 !
1#
1%
b111001 &
b111001 '
#1465000000
0#
0%
#1470000000
b111010 !
1#
1%
b111010 &
b111010 '
#1475000000
0#
0%
#1480000000
b111011 !
1#
1%
b111011 &
b111011 '
#1485000000
0#
0%
#1490000000
b111100 !
1#
1%
b111100 &
b111100 '
#1495000000
0#
0%
#1500000000
b111101 !
1#
1%
b111101 &
b111101 '
#1505000000
0#
0%
#1510000000
b111110 !
1#
1%
b111110 &
b111110 '
#1515000000
0#
0%
#1520000000
b111111 !
1#
1%
b111111 &
b111111 '
#1525000000
0#
0%
#1530000000
b1000000 !
1#
1%
b1000000 &
b1000000 '
#1535000000
0#
0%
#1540000000
b1000001 !
1#
1%
b1000001 &
b1000001 '
#1545000000
0#
0%
#1550000000
b1000010 !
1#
1%
b1000010 &
b1000010 '
#1555000000
0#
0%
#1560000000
b1000011 !
1#
1%
b1000011 &
b1000011 '
#1565000000
0#
0%
#1570000000
b1000100 !
1#
1%
b1000100 &
b1000100 '
#1575000000
0#
0%
#1580000000
b1000101 !
1#
1%
b1000101 &
b1000101 '
#1585000000
0#
0%
#1590000000
b1000110 !
1#
1%
b1000110 &
b1000110 '
#1595000000
0#
0%
#1600000000
b1000111 !
1#
1%
b1000111 &
b1000111 '
#1605000000
0#
0%
#1610000000
b1001000 !
1#
1%
b1001000 &
b1001000 '
#1615000000
0#
0%
#1620000000
b1001001 !
1#
1%
b1001001 &
b1001001 '
#1625000000
0#
0%
#1630000000
b1001010 !
1#
1%
b1001010 &
b1001010 '
#1635000000
0#
0%
#1640000000
b1001011 !
1#
1%
b1001011 &
b1001011 '
#1645000000
0#
0%
#1650000000
b1001100 !
1#
1%
b1001100 &
b1001100 '
#1655000000
0#
0%
#1660000000
b1001101 !
1#
1%
b1001101 &
b1001101 '
#1665000000
0#
0%
#1670000000
b1001110 !
1#
1%
b1001110 &
b1001110 '
#1675000000
0#
0%
#1680000000
b1001111 !
1#
1%
b1001111 &
b1001111 '
#1685000000
0#
0%
#1690000000
b1010000 !
1#
1%
b1010000 &
b1010000 '
#1695000000
0#
0%
#1700000000
b1010001 !
1#
1%
b1010001 &
b1010001 '
#1705000000
0#
0%
#1710000000
b1010010 !
1#
1%
b1010010 &
b1010010 '
#1715000000
0#
0%
#1720000000
b1010011 !
1#
1%
b1010011 &
b1010011 '
#1725000000
0#
0%
#1730000000
b1010100 !
1#
1%
b1010100 &
b1010100 '
#1735000000
0#
0%
#1740000000
b1010101 !
1#
1%
b1010101 &
b1010101 '
#1745000000
0#
0%
#1750000000
b1010110 !
1#
1%
b1010110 &
b1010110 '
#1755000000
0#
0%
#1760000000
b1010111 !
1#
1%
b1010111 &
b1010111 '
#1765000000
0#
0%
#1770000000
b1011000 !
1#
1%
b1011000 &
b1011000 '
#1775000000
0#
0%
#1780000000
b0 !
1#
1%
b0 &
b0 '
#1785000000
0#
0%
#1790000000
b1 !
1#
1%
b1 &
b1 '
#1795000000
0#
0%
#1800000000
b10 !
1#
1%
b10 &
b10 '
#1805000000
0#
0%
#1810000000
b11 !
1#
1%
b11 &
b11 '
#1815000000
0#
0%
#1820000000
b100 !
1#
1%
b100 &
b100 '
#1825000000
0#
0%
#1830000000
b101 !
1#
1%
b101 &
b101 '
#1835000000
0#
0%
#1840000000
b110 !
1#
1%
b110 &
b110 '
#1845000000
0#
0%
#1850000000
b111 !
1#
1%
b111 &
b111 '
#1855000000
0#
0%
#1860000000
b1000 !
1#
1%
b1000 &
b1000 '
#1865000000
0#
0%
#1870000000
b1001 !
1#
1%
b1001 &
b1001 '
#1875000000
0#
0%
#1880000000
b1010 !
1#
1%
b1010 &
b1010 '
#1885000000
0#
0%
#1890000000
b1011 !
1#
1%
b1011 &
b1011 '
#1895000000
0#
0%
#1900000000
b1100 !
1#
1%
b1100 &
b1100 '
#1905000000
0#
0%
#1910000000
b1101 !
1#
1%
b1101 &
b1101 '
#1915000000
0#
0%
#1920000000
b1110 !
1#
1%
b1110 &
b1110 '
#1925000000
0#
0%
#1930000000
b1111 !
1#
1%
b1111 &
b1111 '
#1935000000
0#
0%
#1940000000
b10000 !
1#
1%
b10000 &
b10000 '
#1945000000
0#
0%
#1950000000
b10001 !
1#
1%
b10001 &
b10001 '
#1955000000
0#
0%
#1960000000
b10010 !
1#
1%
b10010 &
b10010 '
#1965000000
0#
0%
#1970000000
b10011 !
1#
1%
b10011 &
b10011 '
#1975000000
0#
0%
#1980000000
b10100 !
1#
1%
b10100 &
b10100 '
#1985000000
0#
0%
#1990000000
b10101 !
1#
1%
b10101 &
b10101 '
#1995000000
0#
0%
#2000000000
b10110 !
1#
1%
b10110 &
b10110 '
#2005000000
0#
0%
#2010000000
b10111 !
1#
1%
b10111 &
b10111 '
#2015000000
0#
0%
#2020000000
b11000 !
1#
1%
b11000 &
b11000 '
#2025000000
0#
0%
#2030000000
b11001 !
1#
1%
b11001 &
b11001 '
#2035000000
0#
0%
#2040000000
b11010 !
1#
1%
b11010 &
b11010 '
#2045000000
0#
0%
#2050000000
b11011 !
1#
1%
b11011 &
b11011 '
#2055000000
0#
0%
#2060000000
b11100 !
1#
1%
b11100 &
b11100 '
#2065000000
0#
0%
#2070000000
b11101 !
1#
1%
b11101 &
b11101 '
#2075000000
0#
0%
#2080000000
b11110 !
1#
1%
b11110 &
b11110 '
#2085000000
0#
0%
#2090000000
b11111 !
1#
1%
b11111 &
b11111 '
#2095000000
0#
0%
#2100000000
b100000 !
1#
1%
b100000 &
b100000 '
#2105000000
0#
0%
#2110000000
b100001 !
1#
1%
b100001 &
b100001 '
#2115000000
0#
0%
#2120000000
b100010 !
1#
1%
b100010 &
b100010 '
#2125000000
0#
0%
#2130000000
b100011 !
1#
1%
b100011 &
b100011 '
#2135000000
0#
0%
#2140000000
b100100 !
1#
1%
b100100 &
b100100 '
#2145000000
0#
0%
#2150000000
b100101 !
1#
1%
b100101 &
b100101 '
#2155000000
0#
0%
#2160000000
b100110 !
1#
1%
b100110 &
b100110 '
#2165000000
0#
0%
#2170000000
b100111 !
1#
1%
b100111 &
b100111 '
#2175000000
0#
0%
#2180000000
b101000 !
1#
1%
b101000 &
b101000 '
#2185000000
0#
0%
#2190000000
b101001 !
1#
1%
b101001 &
b101001 '
#2195000000
0#
0%
#2200000000
b101010 !
1#
1%
b101010 &
b101010 '
#2205000000
0#
0%
#2210000000
b101011 !
1#
1%
b101011 &
b101011 '
#2215000000
0#
0%
#2220000000
b101100 !
1#
1%
b101100 &
b101100 '
#2225000000
0#
0%
#2230000000
b101101 !
1#
1%
b101101 &
b101101 '
#2235000000
0#
0%
#2240000000
b101110 !
1#
1%
b101110 &
b101110 '
#2245000000
0#
0%
#2250000000
b101111 !
1#
1%
b101111 &
b101111 '
#2255000000
0#
0%
#2260000000
b110000 !
1#
1%
b110000 &
b110000 '
#2265000000
0#
0%
#2270000000
b110001 !
1#
1%
b110001 &
b110001 '
#2275000000
0#
0%
#2280000000
b110010 !
1#
1%
b110010 &
b110010 '
#2285000000
0#
0%
#2290000000
b110011 !
1#
1%
b110011 &
b110011 '
#2295000000
0#
0%
#2300000000
b110100 !
1#
1%
b110100 &
b110100 '
#2305000000
0#
0%
#2310000000
b110101 !
1#
1%
b110101 &
b110101 '
#2315000000
0#
0%
#2320000000
b110110 !
1#
1%
b110110 &
b110110 '
#2325000000
0#
0%
#2330000000
b110111 !
1#
1%
b110111 &
b110111 '
#2335000000
0#
0%
#2340000000
b111000 !
1#
1%
b111000 &
b111000 '
#2345000000
0#
0%
#2350000000
b111001 !
1#
1%
b111001 &
b111001 '
#2355000000
0#
0%
#2360000000
b111010 !
1#
1%
b111010 &
b111010 '
#2365000000
0#
0%
#2370000000
b111011 !
1#
1%
b111011 &
b111011 '
#2375000000
0#
0%
#2380000000
b111100 !
1#
1%
b111100 &
b111100 '
#2385000000
0#
0%
#2390000000
b111101 !
1#
1%
b111101 &
b111101 '
#2395000000
0#
0%
#2400000000
b111110 !
1#
1%
b111110 &
b111110 '
#2405000000
0#
0%
#2410000000
b111111 !
1#
1%
b111111 &
b111111 '
#2415000000
0#
0%
#2420000000
b1000000 !
1#
1%
b1000000 &
b1000000 '
#2425000000
0#
0%
#2430000000
b1000001 !
1#
1%
b1000001 &
b1000001 '
#2435000000
0#
0%
#2440000000
b1000010 !
1#
1%
b1000010 &
b1000010 '
#2445000000
0#
0%
#2450000000
b1000011 !
1#
1%
b1000011 &
b1000011 '
#2455000000
0#
0%
#2460000000
b1000100 !
1#
1%
b1000100 &
b1000100 '
#2465000000
0#
0%
#2470000000
b1000101 !
1#
1%
b1000101 &
b1000101 '
#2475000000
0#
0%
#2480000000
b1000110 !
1#
1%
b1000110 &
b1000110 '
#2485000000
0#
0%
#2490000000
b1000111 !
1#
1%
b1000111 &
b1000111 '
#2495000000
0#
0%
#2500000000
b1001000 !
1#
1%
b1001000 &
b1001000 '
#2505000000
0#
0%
#2510000000
b1001001 !
1#
1%
b1001001 &
b1001001 '
#2515000000
0#
0%
#2520000000
b1001010 !
1#
1%
b1001010 &
b1001010 '
#2525000000
0#
0%
#2530000000
b1001011 !
1#
1%
b1001011 &
b1001011 '
#2535000000
0#
0%
#2540000000
b1001100 !
1#
1%
b1001100 &
b1001100 '
#2545000000
0#
0%
#2550000000
b1001101 !
1#
1%
b1001101 &
b1001101 '
#2555000000
0#
0%
#2560000000
b1001110 !
1#
1%
b1001110 &
b1001110 '
#2565000000
0#
0%
#2570000000
b1001111 !
1#
1%
b1001111 &
b1001111 '
#2575000000
0#
0%
#2580000000
b1010000 !
1#
1%
b1010000 &
b1010000 '
#2585000000
0#
0%
#2590000000
b1010001 !
1#
1%
b1010001 &
b1010001 '
#2595000000
0#
0%
#2600000000
b1010010 !
1#
1%
b1010010 &
b1010010 '
#2605000000
0#
0%
#2610000000
b1010011 !
1#
1%
b1010011 &
b1010011 '
#2615000000
0#
0%
#2620000000
b1010100 !
1#
1%
b1010100 &
b1010100 '
#2625000000
0#
0%
#2630000000
b1010101 !
1#
1%
b1010101 &
b1010101 '
#2635000000
0#
0%
#2640000000
b1010110 !
1#
1%
b1010110 &
b1010110 '
#2645000000
0#
0%
#2650000000
b1010111 !
1#
1%
b1010111 &
b1010111 '
#2655000000
0#
0%
#2660000000
b1011000 !
1#
1%
b1011000 &
b1011000 '
#2665000000
0#
0%
#2670000000
b0 !
1#
1%
b0 &
b0 '
#2675000000
0#
0%
#2680000000
b1 !
1#
1%
b1 &
b1 '
#2685000000
0#
0%
#2690000000
b10 !
1#
1%
b10 &
b10 '
#2695000000
0#
0%
#2700000000
b11 !
1#
1%
b11 &
b11 '
#2705000000
0#
0%
#2710000000
b100 !
1#
1%
b100 &
b100 '
#2715000000
0#
0%
#2720000000
b101 !
1#
1%
b101 &
b101 '
#2725000000
0#
0%
#2730000000
b110 !
1#
1%
b110 &
b110 '
#2735000000
0#
0%
#2740000000
b111 !
1#
1%
b111 &
b111 '
#2745000000
0#
0%
#2750000000
b1000 !
1#
1%
b1000 &
b1000 '
#2755000000
0#
0%
#2760000000
b1001 !
1#
1%
b1001 &
b1001 '
#2765000000
0#
0%
#2770000000
b1010 !
1#
1%
b1010 &
b1010 '
#2775000000
0#
0%
#2780000000
b1011 !
1#
1%
b1011 &
b1011 '
#2785000000
0#
0%
#2790000000
b1100 !
1#
1%
b1100 &
b1100 '
#2795000000
0#
0%
#2800000000
b1101 !
1#
1%
b1101 &
b1101 '
#2805000000
0#
0%
#2810000000
b1110 !
1#
1%
b1110 &
b1110 '
#2815000000
0#
0%
#2820000000
b1111 !
1#
1%
b1111 &
b1111 '
#2825000000
0#
0%
#2830000000
b10000 !
1#
1%
b10000 &
b10000 '
#2835000000
0#
0%
#2840000000
b10001 !
1#
1%
b10001 &
b10001 '
#2845000000
0#
0%
#2850000000
b10010 !
1#
1%
b10010 &
b10010 '
#2855000000
0#
0%
#2860000000
b10011 !
1#
1%
b10011 &
b10011 '
#2865000000
0#
0%
#2870000000
b10100 !
1#
1%
b10100 &
b10100 '
#2875000000
0#
0%
#2880000000
b10101 !
1#
1%
b10101 &
b10101 '
#2885000000
0#
0%
#2890000000
b10110 !
1#
1%
b10110 &
b10110 '
#2895000000
0#
0%
#2900000000
b10111 !
1#
1%
b10111 &
b10111 '
#2905000000
0#
0%
#2910000000
b11000 !
1#
1%
b11000 &
b11000 '
#2915000000
0#
0%
#2920000000
b11001 !
1#
1%
b11001 &
b11001 '
#2925000000
0#
0%
#2930000000
b11010 !
1#
1%
b11010 &
b11010 '
#2935000000
0#
0%
#2940000000
b11011 !
1#
1%
b11011 &
b11011 '
#2945000000
0#
0%
#2950000000
b11100 !
1#
1%
b11100 &
b11100 '
#2955000000
0#
0%
#2960000000
b11101 !
1#
1%
b11101 &
b11101 '
#2965000000
0#
0%
#2970000000
b11110 !
1#
1%
b11110 &
b11110 '
#2975000000
0#
0%
#2980000000
b11111 !
1#
1%
b11111 &
b11111 '
#2985000000
0#
0%
#2990000000
b100000 !
1#
1%
b100000 &
b100000 '
#2995000000
0#
0%
#3000000000
b100001 !
1#
1%
b100001 &
b100001 '
#3005000000
0#
0%
#3010000000
b100010 !
1#
1%
b100010 &
b100010 '
#3015000000
0#
0%
#3020000000
b100011 !
1#
1%
b100011 &
b100011 '
#3025000000
0#
0%
#3030000000
b100100 !
1#
1%
b100100 &
b100100 '
#3035000000
0#
0%
#3040000000
b100101 !
1#
1%
b100101 &
b100101 '
#3045000000
0#
0%
#3050000000
b100110 !
1#
1%
b100110 &
b100110 '
#3055000000
0#
0%
#3060000000
b100111 !
1#
1%
b100111 &
b100111 '
#3065000000
0#
0%
#3070000000
b101000 !
1#
1%
b101000 &
b101000 '
#3075000000
0#
0%
#3080000000
b101001 !
1#
1%
b101001 &
b101001 '
#3085000000
0#
0%
#3090000000
b101010 !
1#
1%
b101010 &
b101010 '
#3095000000
0#
0%
#3100000000
b101011 !
1#
1%
b101011 &
b101011 '
#3105000000
0#
0%
#3110000000
b101100 !
1#
1%
b101100 &
b101100 '
#3115000000
0#
0%
#3120000000
b101101 !
1#
1%
b101101 &
b101101 '
#3125000000
0#
0%
#3130000000
b101110 !
1#
1%
b101110 &
b101110 '
#3135000000
0#
0%
#3140000000
b101111 !
1#
1%
b101111 &
b101111 '
#3145000000
0#
0%
#3150000000
b110000 !
1#
1%
b110000 &
b110000 '
#3155000000
0#
0%
#3160000000
b110001 !
1#
1%
b110001 &
b110001 '
#3165000000
0#
0%
#3170000000
b110010 !
1#
1%
b110010 &
b110010 '
#3175000000
0#
0%
#3180000000
b110011 !
1#
1%
b110011 &
b110011 '
#3185000000
0#
0%
#3190000000
b110100 !
1#
1%
b110100 &
b110100 '
#3195000000
0#
0%
#3200000000
b110101 !
1#
1%
b110101 &
b110101 '
#3205000000
0#
0%
#3210000000
b110110 !
1#
1%
b110110 &
b110110 '
#3215000000
0#
0%
#3220000000
b110111 !
1#
1%
b110111 &
b110111 '
#3225000000
0#
0%
#3230000000
b111000 !
1#
1%
b111000 &
b111000 '
#3235000000
0#
0%
#3240000000
b111001 !
1#
1%
b111001 &
b111001 '
#3245000000
0#
0%
#3250000000
b111010 !
1#
1%
b111010 &
b111010 '
#3255000000
0#
0%
#3260000000
b111011 !
1#
1%
b111011 &
b111011 '
#3265000000
0#
0%
#3270000000
b111100 !
1#
1%
b111100 &
b111100 '
#3275000000
0#
0%
#3280000000
b111101 !
1#
1%
b111101 &
b111101 '
#3285000000
0#
0%
#3290000000
b111110 !
1#
1%
b111110 &
b111110 '
#3295000000
0#
0%
#3300000000
b111111 !
1#
1%
b111111 &
b111111 '
#3305000000
0#
0%
#3310000000
b1000000 !
1#
1%
b1000000 &
b1000000 '
#3315000000
0#
0%
#3320000000
b1000001 !
1#
1%
b1000001 &
b1000001 '
#3325000000
0#
0%
#3330000000
b1000010 !
1#
1%
b1000010 &
b1000010 '
#3335000000
0#
0%
